{
  "submission_id": "sub_fixture_contract_001",
  "document_id": "doc_fixture_contract_001",
  "client_id": "client_fixture_001",
  "client_legal_name": "CLIENTE DEMO, S.A. DE C.V.",
  "vendor_id": "vendor_fixture_002",
  "vendor_legal_name": "ARTURO VILLAGRÁN JIMÉNEZ",
  "vendor_rfc": "VIJA900101XXX",
  "provider_nomenclature": "ARTURO VILLAGRÁN JIMÉNEZ",
  "requirement_id": "req_fixture_contract",
  "period_id": "period_expediente_corporativo",
  "document_type_code": "contrato_prestacion_servicios",
  "expected_document_type_code": "contrato_prestacion_servicios",
  "expected_institution": "interno_cliente",
  "original_filename": "ARTURO_VILLAGRAN_JIMENEZ_Contrato_Prestacion_Servicios.pdf",
  "proposed_document_name": "ARTURO VILLAGRÁN JIMÉNEZ Contrato Prestación Servicios",
  "proposed_pdf_file_name": "ARTURO VILLAGRÁN JIMÉNEZ Contrato Prestación Servicios.pdf",
  "sha256": "1111111111111111111111111111111111111111111111111111111111111111",
  "mime_type": "application/pdf",
  "size_bytes": 512000,
  "page_count": 18,
  "uploaded_at": "2026-05-13T12:30:00Z",
  "source_form": "fixture_only_no_real_jotform",
  "storage_key": "fixtures/no-real-document/contrato-prestacion-servicios.pdf",
  "file_url_for_reviewer": null,
  "fixture_notice": "Synthetic fixture. Does not contain real client, provider, fiscal, labor, payroll, or legal data."
}
